{"assets":{"247E4105217753054CC6B54C7B9DB43D":{"type":"texture","index":0,"assetRequest":{"type":"slide","state":"contents","slide":"none"},"url":{"native":"assets\/9FCA0C1D-2F0A-4FBE-96DD-E9DB553F7C3F.pdf"},"width":1920,"height":1080},"5BA6DF7ACEF516F7DAB78587CF30CE20":{"type":"texture","index":1,"assetRequest":{"type":"slide","state":"contents","slide":"none"},"url":{"native":"assets\/9FCA0C1D-2F0A-4FBE-96DD-E9DB553F7C3F.pdf"},"width":1920,"height":1080}},"events":[{"effects":[{"beginTime":0,"baseLayer":{"animations":[],"initialState":{"affineTransform":[1,0,0,1,0,0],"masksToBounds":false,"rotation":0,"scale":1,"position":{"pointX":960,"pointY":540},"width":1920,"sublayerTransform":[1,0,0,0,0,1,0,0,0,0,1,0,0,0,0,1],"contentsRect":{"y":0,"x":0,"width":1,"height":1},"opacity":1,"edgeAntialiasingMask":251658240,"height":1080,"hidden":false,"anchorPoint":{"pointX":0.5,"pointY":0.5}},"objectID":"0","layers":[{"animations":[],"initialState":{"affineTransform":[1,0,0,1,0,0],"masksToBounds":false,"rotation":0,"scale":1,"position":{"pointX":960,"pointY":540},"width":1920,"sublayerTransform":[1,0,0,0,0,1,0,0,0,0,1,-0.00035007912466775983,0,0,0,1],"contentsRect":{"y":0,"x":0,"width":1,"height":1},"opacity":1,"edgeAntialiasingMask":251658240,"height":1080,"hidden":false,"anchorPoint":{"pointX":0.5,"pointY":0.5}},"layers":[{"animations":[],"layers":[],"texturedRectangle":{"isBackgroundTexture":false,"singleTextureOpacity":1,"textureType":0,"textBaseline":0,"textXHeight":0,"isVerticalText":false},"initialState":{"affineTransform":[1,0,0,1,0,0],"masksToBounds":false,"rotation":0,"scale":1,"position":{"pointX":960,"pointY":540},"width":1920,"sublayerTransform":[1,0,0,0,0,1,0,0,0,0,1,0,0,0,0,1],"contentsRect":{"y":0,"x":0,"width":1,"height":1},"opacity":1,"edgeAntialiasingMask":0,"height":1080,"hidden":false,"anchorPoint":{"pointX":0.5,"pointY":0.5}},"texture":"5BA6DF7ACEF516F7DAB78587CF30CE20"},{"animations":[{"timeOffset":0,"from":{"scalar":false},"beginTime":0,"repeatCount":0,"fillMode":"both","property":"hidden","autoreverses":false,"duration":0.01,"to":{"scalar":true}}],"layers":[],"texturedRectangle":{"isBackgroundTexture":false,"singleTextureOpacity":1,"textureType":0,"textBaseline":0,"textXHeight":0,"isVerticalText":false},"initialState":{"affineTransform":[1,0,0,1,0,0],"masksToBounds":false,"rotation":0,"scale":1,"position":{"pointX":960,"pointY":540},"width":1920,"sublayerTransform":[1,0,0,0,0,1,0,0,0,0,1,0,0,0,0,1],"contentsRect":{"y":0,"x":0,"width":1,"height":1},"opacity":1,"edgeAntialiasingMask":0,"height":1080,"hidden":false,"anchorPoint":{"pointX":0.5,"pointY":0.5}},"texture":"247E4105217753054CC6B54C7B9DB43D"}]}]},"effects":[],"duration":0.01,"type":"transition","name":"none","objectID":"0"}],"automaticPlay":false,"hyperlinks":[],"accessibility":[{"text":"T2","targetRectangle":{"y":96.75,"x":84.125,"width":92.903999999999996,"height":101}},{"text":"Github","targetRectangle":{"y":567.90484619140625,"x":653.6537447814942,"width":68.023999999999887,"height":26.361846923828125}},{"text":"페이지","targetRectangle":{"y":594.90484619140625,"x":659.12074478149418,"width":57.089999999999918,"height":27}},{"text":"교육 과정 운영","targetRectangle":{"y":356.28549194335938,"x":719.51259094238276,"width":172.38000000000011,"height":38.619952321052551}},{"text":"Team Building","targetRectangle":{"y":458.09515380859375,"x":767.71454263305668,"width":83.13799999999992,"height":53.361846923828125}},{"text":"앱개발 능력","targetRectangle":{"y":356.28549194335938,"x":1113.7820416259765,"width":138.09000000000015,"height":38.619952321052551}},{"text":"포스터 세션","targetRectangle":{"y":471.09515380859375,"x":880.2683404846191,"width":101.26600000000008,"height":28.187965035438538}},{"text":"지식장터","targetRectangle":{"y":575.54913330078125,"x":771.2235426330567,"width":76.119999999999891,"height":27}},{"text":"앱스토어 ","targetRectangle":{"y":560.54913330078125,"x":892.8413404846192,"width":82.235999999999876,"height":28.187965035438538}},{"text":"준비","targetRectangle":{"y":589.37525141239166,"x":911.87134048461917,"width":38.059999999999945,"height":27}},{"text":"Git 운영","targetRectangle":{"y":662.71453857421875,"x":650.91474478149416,"width":73.501999999999953,"height":28.187965035438538}},{"text":"- 이슈와 브렌치","targetRectangle":{"y":691.54065668582916,"x":639.2107447814941,"width":96.909999999999968,"height":55.826118111610413}},{"text":"회고","targetRectangle":{"y":472.09515380859375,"x":668.63574478149417,"width":38.059999999999945,"height":27}},{"text":"HOF ","targetRectangle":{"y":458.09515380859375,"x":1034.2791603088378,"width":51.766000000000076,"height":26.361846923828125}},{"text":"비행기","targetRectangle":{"y":485.09515380859375,"x":1028.5591603088378,"width":57.090000000000146,"height":27}}],"baseLayer":{"animations":[],"initialState":{"affineTransform":[1,0,0,1,0,0],"masksToBounds":false,"rotation":0,"scale":1,"position":{"pointX":960,"pointY":540},"width":1920,"sublayerTransform":[1,0,0,0,0,1,0,0,0,0,1,0,0,0,0,1],"contentsRect":{"y":0,"x":0,"width":1,"height":1},"opacity":1,"edgeAntialiasingMask":251658240,"height":1080,"hidden":false,"anchorPoint":{"pointX":0.5,"pointY":0.5}},"objectID":"0","layers":[{"animations":[],"initialState":{"affineTransform":[1,0,0,1,0,0],"masksToBounds":false,"rotation":0,"scale":1,"position":{"pointX":960,"pointY":540},"width":1920,"sublayerTransform":[1,0,0,0,0,1,0,0,0,0,1,-0.00035007912466775983,0,0,0,1],"contentsRect":{"y":0,"x":0,"width":1,"height":1},"opacity":1,"edgeAntialiasingMask":251658240,"height":1080,"hidden":false,"anchorPoint":{"pointX":0.5,"pointY":0.5}},"layers":[{"animations":[],"layers":[],"texturedRectangle":{"isBackgroundTexture":false,"singleTextureOpacity":1,"textureType":0,"textBaseline":0,"textXHeight":0,"isVerticalText":false},"initialState":{"affineTransform":[1,0,0,1,0,0],"masksToBounds":false,"rotation":0,"scale":1,"position":{"pointX":960,"pointY":540},"width":1920,"sublayerTransform":[1,0,0,0,0,1,0,0,0,0,1,0,0,0,0,1],"contentsRect":{"y":0,"x":0,"width":1,"height":1},"opacity":1,"edgeAntialiasingMask":0,"height":1080,"hidden":false,"anchorPoint":{"pointX":0.5,"pointY":0.5}},"texture":"247E4105217753054CC6B54C7B9DB43D"}]}]}}]}